finance_calculater/__init__.py
finance_calculater/__main__.py
finance_calculater/calculator.py
finance_calculator_30-0.1.dist-info/METADATA
finance_calculator_30-0.1.dist-info/WHEEL
finance_calculator_30-0.1.dist-info/entry_points.txt
finance_calculator_30-0.1.dist-info/top_level.txt
finance_calculator_30-0.1.dist-info/RECORD
