Metadata-Version: 2.1
Name: finance-calculator-30
Version: 0.1
Summary: A package for calculating net profit and ROI.
Author: grisha123invent
Author-email: grig.perev@gamil.com
